elliptio-0.2.1.dist-info/METADATA
elliptio-0.2.1.dist-info/WHEEL
elliptio-0.2.1.dist-info/licenses/LICENSE
elliptio/__init__.py
elliptio/adapters/__init__.py
elliptio/adapters/db.py
elliptio/adapters/db.sqlite
elliptio/adapters/fs.py
elliptio/adapters/id_creator.py
elliptio/adapters/tmp1.ipynb
elliptio/adapters/tracker.py
elliptio/composite.py
elliptio/handler.py
elliptio/interfaces.py
elliptio-0.2.1.dist-info/RECORD
