Metadata-Version: 2.1
Name: elliptio
Version: 0.2.1
Home-page: https://github.com/cgebbe/elliptio_data_lake
Author: Christian Gebbe
License: MIT
Project-URL: Homepage, https://github.com/cgebbe/elliptio_data_lake
Requires-Python: >=3.8
Requires-Dist: pandas
Requires-Dist: sqlalchemy
Requires-Dist: fsspec
Requires-Dist: pyyaml
